LICENSE.txt
README.rst
setup.py
package_zengzh_greet/__init__.py
package_zengzh_greet/main.py
package_zengzh_greet.egg-info/PKG-INFO
package_zengzh_greet.egg-info/SOURCES.txt
package_zengzh_greet.egg-info/dependency_links.txt
package_zengzh_greet.egg-info/top_level.txt